{
  "tree": [
    {
      "tree": [],
      "meta": {
        "name": "Fixings and clearance around opening min 6mm & max 18mm and PEF rod/air seal are within acceptable tolerance level",
        "dependant": false,
        "stepType": "checkpoint-status",
        "type": "step",
        "display": "normal",
        "order": 0
      }
    },
    {
      "tree": [],
      "meta": {
        "name": "Check taping around, before installing the windows and sliders",
        "dependant": false,
        "stepType": "checkpoint-status",
        "type": "step",
        "display": "normal",
        "order": 1
      }
    },
    {
      "tree": [],
      "meta": {
        "name": "Packers to be correctly used and set back to allow continuous air seal",
        "dependant": false,
        "stepType": "checkpoint-status",
        "type": "step",
        "display": "normal",
        "order": 2
      }
    },
    {
      "tree": [],
      "meta": {
        "name": "Jambs level and straight for finishing lines on the side",
        "dependant": false,
        "stepType": "checkpoint-status",
        "type": "step",
        "display": "normal",
        "order": 3
      }
    },
    {
      "tree": [],
      "meta": {
        "name": "Door and window jambs flush to GIB Board",
        "dependant": false,
        "stepType": "checkpoint-status",
        "type": "step",
        "display": "normal",
        "order": 4
      }
    },
    {
      "tree": [],
      "meta": {
        "name": "Check air seal is provided at the rear of the window reveal",
        "dependant": false,
        "stepType": "checkpoint-status",
        "type": "step",
        "display": "normal",
        "order": 5
      }
    },
    {
      "tree": [],
      "meta": {
        "name": "All joints detailed as per attached Detail Document",
        "dependant": false,
        "stepType": "checkpoint-status",
        "type": "step",
        "display": "normal",
        "order": 6
      }
    },
    {
      "tree": [],
      "meta": {
        "name": "All framing completed correctly within tolerance in respective area",
        "dependant": false,
        "stepType": "checkpoint-status",
        "type": "step",
        "display": "normal",
        "order": 7
      }
    },
    {
      "tree": [],
      "meta": {
        "name": "Sill support fixing bars installed for all joinery within acceptable tolerance level",
        "dependant": false,
        "stepType": "checkpoint-status",
        "type": "step",
        "display": "normal",
        "order": 8
      }
    },
    {
      "tree": [],
      "meta": {
        "name": "All windows, sliders and sealant installation completed to specification & within tolerance in respective area(s)",
        "dependant": false,
        "stepType": "checkpoint-status",
        "type": "step",
        "display": "normal",
        "order": 9
      }
    },
    {
      "tree": [
        {
          "tree": [],
          "meta": {
            "stepType": "holdpoint",
            "display": "flat",
            "name": "CLICK AND SEND EMAIL TO FOREMAN TO SIGN FOR RECEIPT OF THE INSPECTION RESULTS",
            "dependant": true,
            "signoffs": true,
            "type": "step",
            "order": 0
          }
        }
      ],
      "meta": {
        "name": "Inspections completed and issued to Foreman",
        "dependant": false,
        "stepType": "checkpoint-status",
        "type": "step",
        "display": "normal",
        "order": 10
      }
    }
  ],
  "meta": {
    "name": "FC - S - Windows, Sliders and Sealants",
    "dependant": true,
    "stepType": "checklist-flat",
    "type": "step",
    "permissions": {
      "addStep": false,
      "addPost": false
    },
    "display": "flat"
  }
}